langchain_arangodb/__init__.py
langchain_arangodb/chains/__init__.py
langchain_arangodb/chains/graph_qa/__init__.py
langchain_arangodb/chains/graph_qa/arangodb.py
langchain_arangodb/chains/graph_qa/prompts.py
langchain_arangodb/chat_message_histories/__init__.py
langchain_arangodb/chat_message_histories/arangodb.py
langchain_arangodb/graphs/__init__.py
langchain_arangodb/graphs/arangodb_graph.py
langchain_arangodb/graphs/graph_document.py
langchain_arangodb/graphs/graph_store.py
langchain_arangodb/py.typed
langchain_arangodb/query_constructors/__init__.py
langchain_arangodb/query_constructors/arangodb.py
langchain_arangodb/vectorstores/__init__.py
langchain_arangodb/vectorstores/arangodb_vector.py
langchain_arangodb/vectorstores/utils.py
langchain_arangodb-2.1.0.dist-info/LICENSE
langchain_arangodb-2.1.0.dist-info/METADATA
langchain_arangodb-2.1.0.dist-info/WHEEL
langchain_arangodb-2.1.0.dist-info/RECORD
