Metadata-Version: 2.1
Name: langchain-arangodb
Version: 2.1.0
Summary: An integration package connecting ArangoDB and LangChain
Home-page: https://github.com/arangoml/langchain-arangodb
License: MIT
Author: ArangoDB
Requires-Python: >=3.10,<4.0
Classifier: License :: OSI Approved :: MIT License
Classifier: Programming Language :: Python :: 3
Classifier: Programming Language :: Python :: 3.10
Classifier: Programming Language :: Python :: 3.11
Classifier: Programming Language :: Python :: 3.12
Requires-Dist: cityhash (>=0.4.8,<0.5.0)
Requires-Dist: langchain (>=0.3.7,<2.0.0)
Requires-Dist: langchain-classic (>=1.0.0,<2.0.0)
Requires-Dist: langchain-core (>=0.3.8,<2.0.0)
Requires-Dist: numpy (>=1.0.0,<3.0.0)
Requires-Dist: python-arango (>=8.0.0,<9.0.0)
Project-URL: Repository, https://github.com/arangoml/langchain-arangodb
Project-URL: Release Notes, https://github.com/arangoml/langchain-arangodb/releases
Project-URL: Source Code, https://github.com/arangoml/langchain-arangodb/tree/main/libs/arangodb
